{
  "updatedAt": "2026-02-04T11:49:12Z",
  "groups": [
    {
      "region": "Македонија",
      "items": [
        {
          "source": "МИА",
          "title": "⚠️ Не може да се вчита (извор/timeout)",
          "link": "https://mia.mk/rss",
          "published": ""
        },
        {
          "source": "Makfax",
          "title": "Гаши во Вашингтон: нагласена  важноста на американското лидерство во зачувувањето на евроатлантската безбедност",
          "link": "https://makfax.com.mk/makedonija/%d0%b3%d0%b0%d1%88%d0%b8-%d0%b2%d0%be-%d0%b2%d0%b0%d1%88%d0%b8%d0%bd%d0%b3%d1%82%d0%be%d0%bd-%d0%bd%d0%b0%d0%b3%d0%bb%d0%b0%d1%81%d0%b5%d0%bd%d0%b0-%d0%b2%d0%b0%d0%b6%d0%bd%d0%be%d1%81%d1%82%d0%b0/",
          "published": "Wed, 04 Feb 2026 11:28:54 +0000"
        },
        {
          "source": "Makfax",
          "title": "Поради јавен собир во прекин сообраќајот кај Плетвар",
          "link": "https://makfax.com.mk/makedonija/%d0%bf%d0%be%d1%80%d0%b0%d0%b4%d0%b8-%d1%98%d0%b0%d0%b2%d0%b5%d0%bd-%d1%81%d0%be%d0%b1%d0%b8%d1%80-%d0%b2%d0%be-%d0%bf%d1%80%d0%b5%d0%ba%d0%b8%d0%bd-%d1%81%d0%be%d0%be%d0%b1%d1%80%d0%b0%d1%9c%d0%b0/",
          "published": "Wed, 04 Feb 2026 11:24:34 +0000"
        },
        {
          "source": "Makfax",
          "title": "Мицкоски: Културата е наш приоритет, оваа година имаме зголемен буџет за половина милијарда денари",
          "link": "https://makfax.com.mk/makedonija/%d0%bc%d0%b8%d1%86%d0%ba%d0%be%d1%81%d0%ba%d0%b8-%d0%ba%d1%83%d0%bb%d1%82%d1%83%d1%80%d0%b0%d1%82%d0%b0-%d0%b5-%d0%bd%d0%b0%d1%88-%d0%bf%d1%80%d0%b8%d0%be%d1%80%d0%b8%d1%82%d0%b5%d1%82-%d0%be%d0%b2/",
          "published": "Wed, 04 Feb 2026 11:18:26 +0000"
        },
        {
          "source": "Makfax",
          "title": "По протестите за „Безбеден град“, Мицкоски најави жесток одговор за секој кој го прекршил законот",
          "link": "https://makfax.com.mk/makedonija/%d0%bf%d0%be-%d0%bf%d1%80%d0%be%d1%82%d0%b5%d1%81%d1%82%d0%b8%d1%82%d0%b5-%d0%b7%d0%b0-%d0%b1%d0%b5%d0%b7%d0%b1%d0%b5%d0%b4%d0%b5%d0%bd-%d0%b3%d1%80%d0%b0%d0%b4-%d0%bc%d0%b8%d1%86/",
          "published": "Wed, 04 Feb 2026 11:17:46 +0000"
        },
        {
          "source": "Makfax",
          "title": "Песков: Арктикот е наш регион, ние сме арктичка држава",
          "link": "https://makfax.com.mk/svet/%d0%bf%d0%b5%d1%81%d0%ba%d0%be%d0%b2-%d0%b0%d1%80%d0%ba%d1%82%d0%b8%d0%ba%d0%be%d1%82-%d0%b5-%d0%bd%d0%b0%d1%88-%d1%80%d0%b5%d0%b3%d0%b8%d0%be%d0%bd-%d0%bd%d0%b8%d0%b5-%d1%81%d0%bc%d0%b5-%d0%b0/",
          "published": "Wed, 04 Feb 2026 11:13:18 +0000"
        },
        {
          "source": "NetPress",
          "title": "Ги запознаваме ретките болести: Шварц – Џампелов синдром",
          "link": "https://netpress.com.mk/gi-zapoznavame-retkite-bolesti-shvarcz-dhampelov-sindrom/",
          "published": "Wed, 04 Feb 2026 11:46:55 +0000"
        },
        {
          "source": "NetPress",
          "title": "Опра Винфри и Рајан Рејнолдс во септември на настани во Букурешт",
          "link": "https://netpress.com.mk/opra-vinfri-i-rajan-rejnolds-vo-septemvri-na-nastani-vo-bukuresht/",
          "published": "Wed, 04 Feb 2026 11:40:33 +0000"
        },
        {
          "source": "NetPress",
          "title": "Украина и Русија ја започнаа втората рунда преговори во Абу Даби",
          "link": "https://netpress.com.mk/ukraina-i-rusija-ja-zapochnaa-vtorata-runda-pregovori-vo-abu-dabi/",
          "published": "Wed, 04 Feb 2026 11:22:28 +0000"
        },
        {
          "source": "NetPress",
          "title": "Видеолотарија Касинос Австрија урива рекорди: Речиси милион и двесте илјади евра исплатени добивки во јануари!",
          "link": "https://netpress.com.mk/videolotarija-kasinos-avstrija-uriva-rekordi-rechisi-milion-i-dveste-iljadi-evra-isplateni-dobivki-vo-januari/",
          "published": "Wed, 04 Feb 2026 11:20:19 +0000"
        },
        {
          "source": "NetPress",
          "title": "Вооружени лица убија најмалку 35 лица во Нигерија",
          "link": "https://netpress.com.mk/vooruzheni-licza-ubija-najmalku-35-licza-vo-nigerija/",
          "published": "Wed, 04 Feb 2026 11:09:50 +0000"
        }
      ]
    },
    {
      "region": "Свет",
      "items": [
        {
          "source": "BBC",
          "title": "Russian attacks on Ukraine energy sites 'particularly depraved', UK PM Starmer says",
          "link": "https://www.bbc.com/news/articles/crley6x0dgzo?at_medium=RSS&at_campaign=rss",
          "published": "Wed, 04 Feb 2026 11:29:22 GMT"
        },
        {
          "source": "BBC",
          "title": "Israeli strikes kill 17 in Gaza, hospitals say, after soldier wounded by gunfire",
          "link": "https://www.bbc.com/news/articles/cpqyg0g5r0po?at_medium=RSS&at_campaign=rss",
          "published": "Wed, 04 Feb 2026 09:30:08 GMT"
        },
        {
          "source": "BBC",
          "title": "Melinda French Gates says ex-husband Bill has questions to answer over Epstein",
          "link": "https://www.bbc.com/news/articles/cr4kyk9nv5lo?at_medium=RSS&at_campaign=rss",
          "published": "Wed, 04 Feb 2026 03:03:13 GMT"
        },
        {
          "source": "BBC",
          "title": "Saif al-Islam Gaddafi, son of ex-Libyan leader, reportedly shot dead",
          "link": "https://www.bbc.com/news/articles/cp37g4xgkxdo?at_medium=RSS&at_campaign=rss",
          "published": "Wed, 04 Feb 2026 01:37:22 GMT"
        },
        {
          "source": "BBC",
          "title": "'I've never hit anything so hard': What it's like to be attacked by a shark",
          "link": "https://www.bbc.com/news/articles/cwy8ded4890o?at_medium=RSS&at_campaign=rss",
          "published": "Wed, 04 Feb 2026 05:58:29 GMT"
        },
        {
          "source": "Al Jazeera",
          "title": "Gunmen kill more than 30 people in Nigeria’s Kwara State: Authorities",
          "link": "https://www.aljazeera.com/news/2026/2/4/gunmen-kill-more-than-30-people-in-nigerias-kwara-state-authorities?traffic_source=rss",
          "published": "Wed, 04 Feb 2026 11:21:36 +0000"
        },
        {
          "source": "Al Jazeera",
          "title": "Gorton and Denton by-election tests Labour’s grip on heartland voters",
          "link": "https://www.aljazeera.com/news/2026/2/4/gorton-and-denton-by-election-tests-labours-grip-on-heartland-voters?traffic_source=rss",
          "published": "Wed, 04 Feb 2026 10:48:39 +0000"
        },
        {
          "source": "Al Jazeera",
          "title": "‘Health crime’: Aoun slams Israel over spraying chemicals in south Lebanon",
          "link": "https://www.aljazeera.com/news/2026/2/4/health-crime-aoun-slams-israel-over-spraying-chemicals-in-south-lebanon?traffic_source=rss",
          "published": "Wed, 04 Feb 2026 10:33:23 +0000"
        },
        {
          "source": "Al Jazeera",
          "title": "A simple guide to playing cricket",
          "link": "https://www.aljazeera.com/sports/2026/2/4/a-simple-guide-to-playing-cricket?traffic_source=rss",
          "published": "Wed, 04 Feb 2026 10:24:40 +0000"
        },
        {
          "source": "Al Jazeera",
          "title": "ICE agents have no operational police role in Winter Olympics: Italy",
          "link": "https://www.aljazeera.com/sports/2026/2/4/ice-agents-have-no-operational-police-role-in-winter-olympics-italy?traffic_source=rss",
          "published": "Wed, 04 Feb 2026 10:13:47 +0000"
        }
      ]
    }
  ]
}