{
  "updatedAt": "2026-01-29T20:55:56Z",
  "groups": [
    {
      "region": "Македонија",
      "items": [
        {
          "source": "МИА",
          "title": "⚠️ Не може да се вчита (извор/timeout)",
          "link": "https://mia.mk/rss",
          "published": ""
        },
        {
          "source": "Makfax",
          "title": "Трамп тврди дека Путин се согласил на прекин на огнот, пристигна првата реакција на Зеленски",
          "link": "https://makfax.com.mk/svet/%d1%82%d1%80%d0%b0%d0%bc%d0%bf-%d1%82%d0%b2%d1%80%d0%b4%d0%b8-%d0%b4%d0%b5%d0%ba%d0%b0-%d0%bf%d1%83%d1%82%d0%b8%d0%bd-%d1%81%d0%b5-%d1%81%d0%be%d0%b3%d0%bb%d0%b0%d1%81%d0%b8%d0%bb-%d0%bd%d0%b0-%d0%bf/",
          "published": "Thu, 29 Jan 2026 20:15:07 +0000"
        },
        {
          "source": "Makfax",
          "title": "Парламентарното собрание на Советот на Европа донесе одлука за затворање на пост-мониторинг дијалогот со Македонија: „Значаен успех“",
          "link": "https://makfax.com.mk/makedonija/%d0%bf%d0%b0%d1%80%d0%bb%d0%b0%d0%bc%d0%b5%d0%bd%d1%82%d0%b0%d1%80%d0%bd%d0%be%d1%82%d0%be-%d1%81%d0%be%d0%b1%d1%80%d0%b0%d0%bd%d0%b8%d0%b5-%d0%bd%d0%b0-%d1%81%d0%be%d0%b2%d0%b5%d1%82%d0%be%d1%82/",
          "published": "Thu, 29 Jan 2026 20:07:08 +0000"
        },
        {
          "source": "Makfax",
          "title": "(Видео) Исмаил до Љутков: Следува милионска штета по буџетот по ваша вина, кога планирате да си поднесете оставка?",
          "link": "https://makfax.com.mk/makedonija/%d0%b2%d0%b8%d0%b4%d0%b5%d0%be-%d0%b8%d1%81%d0%bc%d0%b0%d0%b8%d0%bb-%d0%b4%d0%be-%d1%99%d1%83%d1%82%d0%ba%d0%be%d0%b2-%d1%81%d0%bb%d0%b5%d0%b4%d1%83%d0%b2%d0%b0-%d0%bc%d0%b8%d0%bb%d0%b8%d0%be%d0%bd/",
          "published": "Thu, 29 Jan 2026 19:19:04 +0000"
        },
        {
          "source": "Makfax",
          "title": "Загреб доделува по 800 евра за новороденче",
          "link": "https://makfax.com.mk/svet/region/%d0%b7%d0%b0%d0%b3%d1%80%d0%b5%d0%b1-%d0%b4%d0%be%d0%b4%d0%b5%d0%bb%d1%83%d0%b2%d0%b0-%d0%bf%d0%be-800-%d0%b5%d0%b2%d1%80%d0%b0-%d0%b7%d0%b0-%d0%bd%d0%be%d0%b2%d0%be%d1%80%d0%be%d0%b4%d0%b5%d0%bd/",
          "published": "Thu, 29 Jan 2026 19:02:08 +0000"
        },
        {
          "source": "Makfax",
          "title": "Роберто Де Зерби ќе добие отказ поради чудо во Лисабон?",
          "link": "https://makfax.com.mk/sport/roberto-de-zerbi-ke-dobie-otkaz-poradi-chudo-vo-lisabon/",
          "published": "Thu, 29 Jan 2026 18:58:33 +0000"
        },
        {
          "source": "NetPress",
          "title": "Србија: Рекордна заплена на дрога, пет тони марихуана вредна до 10 милиони евра",
          "link": "https://netpress.com.mk/srbija-rekordna-zaplena-na-droga-pet-toni-marihuana-vredna-do-10-milioni-evra/",
          "published": "Thu, 29 Jan 2026 20:44:52 +0000"
        },
        {
          "source": "NetPress",
          "title": "Хегсет го информирал Трамп дека Пентагон е подготвен за Иран",
          "link": "https://netpress.com.mk/hegset-go-informiral-tramp-deka-pentagon-e-podgotven-za-iran/",
          "published": "Thu, 29 Jan 2026 20:24:35 +0000"
        },
        {
          "source": "NetPress",
          "title": "Тимо Вернер од Лајпциг се сели во Сан Хозе",
          "link": "https://netpress.com.mk/timo-verner-od-lajpczig-se-seli-vo-san-hoze/",
          "published": "Thu, 29 Jan 2026 20:09:40 +0000"
        },
        {
          "source": "NetPress",
          "title": "Министерството за спорт додели 500 стипендии „Спортска надеж“",
          "link": "https://netpress.com.mk/ministerstvoto-za-sport-dodeli-500-stipendii-sportska-nadezh/",
          "published": "Thu, 29 Jan 2026 19:56:35 +0000"
        },
        {
          "source": "NetPress",
          "title": "ПССЕ го затвори пост-мониторинг дијалогот со Македонија отворен 2000-та, важно институционално признание за напредокот на државата",
          "link": "https://netpress.com.mk/psse-go-zatvori-post-monitoring-dijalogot-so-makedonija-otvoren-2000-ta-vazhno-instituczionalno-priznanie-za-napredokot-na-drzhavata/",
          "published": "Thu, 29 Jan 2026 19:34:21 +0000"
        }
      ]
    },
    {
      "region": "Свет",
      "items": [
        {
          "source": "BBC",
          "title": "EU adds Iran's Revolutionary Guards to terrorist list",
          "link": "https://www.bbc.com/news/articles/c20gypw8enjo?at_medium=RSS&at_campaign=rss",
          "published": "Thu, 29 Jan 2026 16:49:20 GMT"
        },
        {
          "source": "BBC",
          "title": "'I can breathe again' says Israeli hostage held for nearly 500 days in Gaza",
          "link": "https://www.bbc.com/news/articles/c8rm20gm364o?at_medium=RSS&at_campaign=rss",
          "published": "Thu, 29 Jan 2026 16:25:40 GMT"
        },
        {
          "source": "BBC",
          "title": "France moves to abolish concept of marital duty to have sex",
          "link": "https://www.bbc.com/news/articles/cgjwxdz45ywo?at_medium=RSS&at_campaign=rss",
          "published": "Thu, 29 Jan 2026 16:00:41 GMT"
        },
        {
          "source": "BBC",
          "title": "Chips, anyone? German farm gives away millions of potatoes after bumper harvest",
          "link": "https://www.bbc.com/news/articles/c5y2zqer8j2o?at_medium=RSS&at_campaign=rss",
          "published": "Thu, 29 Jan 2026 17:48:24 GMT"
        },
        {
          "source": "BBC",
          "title": "Israeli media cite official accepting Hamas figure of 70,000 war dead",
          "link": "https://www.bbc.com/news/articles/cvgpd1x00exo?at_medium=RSS&at_campaign=rss",
          "published": "Thu, 29 Jan 2026 19:10:20 GMT"
        },
        {
          "source": "Al Jazeera",
          "title": "‘Melania’: What to know about the US first lady’s new documentary",
          "link": "https://www.aljazeera.com/news/2026/1/29/melania-what-to-know-about-the-us-first-ladys-new-documentary?traffic_source=rss",
          "published": "Thu, 29 Jan 2026 20:15:48 +0000"
        },
        {
          "source": "Al Jazeera",
          "title": "France moves to ban social media for users under 15",
          "link": "https://www.aljazeera.com/video/newsfeed/2026/1/29/france-moves-to-ban-social-media-for-users-under-15?traffic_source=rss",
          "published": "Thu, 29 Jan 2026 20:04:58 +0000"
        },
        {
          "source": "Al Jazeera",
          "title": "TotalEnergies restarts $20bn LNG project in Mozambique after 5-year freeze",
          "link": "https://www.aljazeera.com/news/2026/1/29/total-restarts-20bn-lng-project-in-mozambique-after-five-year-freeze?traffic_source=rss",
          "published": "Thu, 29 Jan 2026 20:03:31 +0000"
        },
        {
          "source": "Al Jazeera",
          "title": "Iran slams EU’s ‘terrorist’ designation for IRGC as hypocritical",
          "link": "https://www.aljazeera.com/video/newsfeed/2026/1/29/iran-slams-eus-terrorist-designation-for-irgc-as-hypocritical?traffic_source=rss",
          "published": "Thu, 29 Jan 2026 19:45:28 +0000"
        },
        {
          "source": "Al Jazeera",
          "title": "Former Illinois deputy sentenced to 20 years for US killing of Sonya Massey",
          "link": "https://www.aljazeera.com/news/2026/1/29/former-illinois-deputy-sentenced-to-20-years-for-killing-of-sonya-massey?traffic_source=rss",
          "published": "Thu, 29 Jan 2026 19:28:40 +0000"
        }
      ]
    }
  ]
}